cosmos/overcloud/__init__.py
cosmos/overcloud/dashboard.py
cosmos/overcloud/models.py
enabled/_40_cosmos.py
enabled/_40_router.py.example
enabled/_45_monitoring_panel_group.py
enabled/_50_admin_add_monitoring_panel.py
enabled/_60_admin_add_notification_panel.py
monitoring/__init__.py
monitoring/constants.py
monitoring/forms.py
monitoring/panel.py
monitoring/tables.py
monitoring/urls.py
monitoring/views.py
monitoring/alarms/__init__.py
monitoring/alarms/constants.py
monitoring/alarms/forms.py
monitoring/alarms/panel.py
monitoring/alarms/tables.py
monitoring/alarms/urls.py
monitoring/alarms/views.py
monitoring/alarms/templates/alarms/_scripts.html
monitoring/alarms/templates/alarms/alarm.html
monitoring/alarms/templates/alarms/alarm_history.html
monitoring/alarms/templates/alarms/alarm_meter.html
monitoring/alarms/templates/alarms/index.html
monitoring/alarms/templates/alarms/monitor.html
monitoring/alarms/templates/alarms/monitorng.html
monitoring/alarms/templates/alarms/newmonitor.html
monitoring/alarms/templates/alarms/alarms/_create.html
monitoring/alarms/templates/alarms/alarms/_detail.html
monitoring/alarms/templates/alarms/alarms/_edit.html
monitoring/alarms/templates/alarms/alarms/create.html
monitoring/alarms/templates/alarms/alarms/detail.html
monitoring/alarms/templates/alarms/alarms/edit.html
monitoring/alarms/templates/alarms/alarms/index.html
monitoring/api/__init__.py
monitoring/api/monitor.py
monitoring/notifications/__init__.py
monitoring/notifications/constants.py
monitoring/notifications/forms.py
monitoring/notifications/panel.py
monitoring/notifications/tables.py
monitoring/notifications/urls.py
monitoring/notifications/views.py
monitoring/notifications/templates/notifications/_create.html
monitoring/notifications/templates/notifications/_detail.html
monitoring/notifications/templates/notifications/create.html
monitoring/notifications/templates/notifications/detail.html
monitoring_plugin-1.0.3.dist-info/DESCRIPTION.rst
monitoring_plugin-1.0.3.dist-info/METADATA
monitoring_plugin-1.0.3.dist-info/metadata.json
monitoring_plugin-1.0.3.dist-info/RECORD
monitoring_plugin-1.0.3.dist-info/top_level.txt
monitoring_plugin-1.0.3.dist-info/WHEEL
