Metadata-Version: 2.0
Name: monitoring-plugin
Version: 1.0.3
Summary: OpenStack Monitoring Plugin for Horizon
Home-page: https://github.com/hpcloud-mon/mon-ui
Author: Hewlett-Packard
Author-email: rob.raymond@hp.com
License: UNKNOWN
Platform: UNKNOWN
Classifier: Environment :: Console
Classifier: Intended Audience :: Information Technology
Classifier: Intended Audience :: System Administrators
Classifier: License :: OSI Approved :: Apache Software License
Classifier: Operating System :: POSIX :: Linux
Classifier: Programming Language :: Python
Classifier: Programming Language :: Python :: 2
Classifier: Programming Language :: Python :: 2.7
Classifier: Programming Language :: Python :: 2.6
Classifier: Programming Language :: Python :: 3
Classifier: Programming Language :: Python :: 3.3
